collective/outputfilters/tinymceaccordion/__init__.py
collective/outputfilters/tinymceaccordion/configure.zcml
collective/outputfilters/tinymceaccordion/filter.py
collective/outputfilters/tinymceaccordion/interfaces.py
collective/outputfilters/tinymceaccordion/profiles.zcml
collective/outputfilters/tinymceaccordion/setuphandlers.py
collective/outputfilters/tinymceaccordion/testing.py
collective/outputfilters/tinymceaccordion/locales/README.md
collective/outputfilters/tinymceaccordion/locales/__init__.py
collective/outputfilters/tinymceaccordion/locales/collective.outputfilters.tinymceaccordion.pot
collective/outputfilters/tinymceaccordion/locales/update.py
collective/outputfilters/tinymceaccordion/locales/update.sh
collective/outputfilters/tinymceaccordion/locales/de/LC_MESSAGES/collective.outputfilters.tinymceaccordion.mo
collective/outputfilters/tinymceaccordion/locales/de/LC_MESSAGES/collective.outputfilters.tinymceaccordion.po
collective/outputfilters/tinymceaccordion/locales/en/LC_MESSAGES/collective.outputfilters.tinymceaccordion.mo
collective/outputfilters/tinymceaccordion/locales/en/LC_MESSAGES/collective.outputfilters.tinymceaccordion.po
collective/outputfilters/tinymceaccordion/profiles/default/browserlayer.xml
collective/outputfilters/tinymceaccordion/profiles/default/catalog.xml
collective/outputfilters/tinymceaccordion/profiles/default/metadata.xml
collective/outputfilters/tinymceaccordion/profiles/default/rolemap.xml
collective/outputfilters/tinymceaccordion/profiles/default/registry/main.xml
collective/outputfilters/tinymceaccordion/profiles/uninstall/browserlayer.xml
collective_outputfilters_tinymceaccordion-2.0.0.dist-info/METADATA
collective_outputfilters_tinymceaccordion-2.0.0.dist-info/WHEEL
collective_outputfilters_tinymceaccordion-2.0.0.dist-info/entry_points.txt
collective_outputfilters_tinymceaccordion-2.0.0.dist-info/top_level.txt
collective_outputfilters_tinymceaccordion-2.0.0.dist-info/RECORD
