Metadata-Version: 2.4
Name: collective.outputfilters.tinymceaccordion
Version: 2.0.0
Summary: Addon for Plone 6 - Plone Outputfilter to transform TinyMCE Markup to Bootstrap5 Accordion
Home-page: https://github.com/collective/collective.outputfilters.tinymceaccordion
Author: 1letter
Author-email: 1letter@gmx.de
License: GPL version 2
Project-URL: PyPI, https://pypi.org/project/collective.outputfilters.tinymceaccordion/
Project-URL: Source, https://github.com/collective/collective.outputfilters.tinymceaccordion
Project-URL: Tracker, https://github.com/collective/collective.outputfilters.tinymceaccordion/issues
Keywords: Python Plone CMS
Classifier: Development Status :: 4 - Beta
Classifier: Environment :: Web Environment
Classifier: Framework :: Plone
Classifier: Framework :: Plone :: Addon
Classifier: Framework :: Plone :: 6.0
Classifier: Framework :: Plone :: 6.1
Classifier: Framework :: Plone :: 6.2
Classifier: Programming Language :: Python
Classifier: Programming Language :: Python :: 3.10
Classifier: Programming Language :: Python :: 3.11
Classifier: Programming Language :: Python :: 3.12
Classifier: Programming Language :: Python :: 3.13
Classifier: Operating System :: OS Independent
Classifier: License :: OSI Approved :: GNU General Public License v2 (GPLv2)
Requires-Python: >=3.10
Requires-Dist: setuptools
Requires-Dist: Products.CMFPlone
Requires-Dist: Products.GenericSetup
Requires-Dist: beautifulsoup4
Requires-Dist: plone.base
Requires-Dist: plone.outputfilters
Requires-Dist: plone.registry
Requires-Dist: zope.component
Requires-Dist: zope.i18nmessageid
Requires-Dist: zope.interface
Requires-Dist: zope.publisher
Provides-Extra: test
Requires-Dist: zest.releaser[recommended]; extra == "test"
Requires-Dist: zestreleaser.towncrier; extra == "test"
Requires-Dist: zest.pocompile; extra == "test"
Requires-Dist: plone.app.testing; extra == "test"
Requires-Dist: pytest; extra == "test"
Requires-Dist: pytest-cov; extra == "test"
Requires-Dist: pytest-plone>=0.5.0; extra == "test"
Dynamic: author
Dynamic: author-email
Dynamic: classifier
Dynamic: description
Dynamic: description-content-type
Dynamic: home-page
Dynamic: keywords
Dynamic: license
Dynamic: project-url
Dynamic: provides-extra
Dynamic: requires-dist
Dynamic: requires-python
Dynamic: summary
